{
  "title": "Teaser",
  "titleTemplate": "%s - Teaser",
  "description": "here and there, Exploration of Landscape Aesthetic, Hong Kong Scenic Sites and Cultural Imagination",
  "openGraph": {
    "title": "Teaser",
    "description": "Teaser, here and there, exhibition, Hongkong",
    "type": "website",
    "url": "https://hereandthere.hk/",
    "site_name": "Teaser",
    "images": [
      {
        "url": "/card.png",
        "width": "800",
        "height": "600",
        "alt": "Teaser"
      }
    ]
  },
  "twitter": {
    "handle": "Teaser",
    "site": "Teaser",
    "cardType": "summary_large_image"
  }
}
